binance_cm/__init__.py
binance_eo-1.0.0.dev0.dist-info/METADATA
binance_eo-1.0.0.dev0.dist-info/WHEEL
binance_eo-1.0.0.dev0.dist-info/top_level.txt
binance_eo-1.0.0.dev0.dist-info/RECORD
